clockboard/__init__.py
clockboard/admin.py
clockboard/apps.py
clockboard/auth_hooks.py
clockboard/forms.py
clockboard/models.py
clockboard/urls.py
clockboard/views.py
clockboard/migrations/0001_initial.py
clockboard/migrations/__init__.py
clockboard/static/clockboard/js/clocks.js
clockboard/templates/clockboard/base.html
clockboard/templates/clockboard/clock_board.html
clockboard/templates/clockboard/clocks.html
clockboard/templates/clockboard/dashboard_panel.html
clockboard/templates/clockboard/new_clock.html
clockboard/templates/clockboard/reset_clock.html
aa_clockboard-0.1.0.dist-info/LICENSE
aa_clockboard-0.1.0.dist-info/WHEEL
aa_clockboard-0.1.0.dist-info/METADATA
aa_clockboard-0.1.0.dist-info/RECORD
